{
  "id": "1ev3d5ok5d1xc",
  "type": "work",
  "title": "聖祖仁皇帝庭訓格言",
  "authors": [],
  "collections": [
    "1agpxlq9l8nb4"
  ],
  "books": [
    "11q37qleba96o",
    "11q7m1s72sglc"
  ],
  "additional_titles": [
    "庭訓格言"
  ],
  "indexed_by": [
    {
      "source": "欽定四庫全書總目",
      "source_bid": "1eujf2fs4v280",
      "title_info": "《庭訓格言》·一卷",
      "summary": "雍正八年，世宗憲皇帝追述聖祖仁皇帝天語，親錄成編。凡二百四十有六則，皆實錄聖訓所未及載者。蓋我世宗憲皇帝至孝承顏，特蒙眷注。宮闈問視之暇，從容溫諭，指示獨詳。而帝德同符，心源默合，聆受亦能獨契，故繹舊聞，編摩寶帙，敷由皇極，方軌六經。粵考三皇、五帝以逮於禹、湯、文、武，其佚文遺教，散見於周、秦諸書，而紀錄失真，醇疵互見。故司馬遷有百家稱黃帝，其文不雅馴之說。蓋其識不足以知聖人，故所述不盡合本旨也。是編以聖人之筆記聖人之言，傳述既得精微；又以聖人親聞於聖人，授受尤為親切。垂諸萬世，固當與典謨訓誥共昭法守矣。"
    }
  ],
  "resources": [
    {
      "id": "ctext",
      "name": "CText",
      "url": "https://ctext.org/wiki.pl?if=gb&res=672133",
      "types": [
        "text"
      ]
    },
    {
      "id": "ctext-1",
      "name": "CText",
      "url": "https://ctext.org/wiki.pl?if=gb&res=470195",
      "types": [
        "text"
      ]
    },
    {
      "id": "shidianguji-sikuquanshuben",
      "name": "识典古籍",
      "url": "https://www.shidianguji.com/book/SK1363",
      "metadata": {
        "edition": "四庫全書本",
        "version": "v3",
        "total_page": 197,
        "paragraph_count": 282,
        "check_type": "粗校"
      },
      "types": [
        "text",
        "image"
      ]
    },
    {
      "name": "Internet Archive",
      "id": "internet-archive",
      "url": "https://archive.org/details/q_005_shengzu_v01_0001",
      "types": [
        "image"
      ]
    }
  ],
  "has_text": true,
  "has_image": true
}