{
  "id": "1ev7vo5guna4g",
  "type": "work",
  "title": "黃帝內經",
  "authors": [],
  "juan_count": {
    "number": 18
  },
  "description": {
    "text": "書今殘存。《漢書·藝文志》著錄十八卷。晉皇甫謐《甲乙經·序》云今有《針經》九卷、《素問》九卷，二九十八卷，即《內經》也。後世傳本有《素問》與《靈樞》（即《針經》）。此書託名黃帝，實為周漢之間醫者依託以取重，非黃帝所著。司馬光已辨其偽。其中多數內容屬先秦，馬王堆漢墓出土醫書亦可印證。《四庫全書》著錄《黃帝素問》二十四卷、《靈樞經》十二卷。",
    "sources": [
      "溫浚源《漢書藝文志講要》"
    ]
  },
  "related_works": [
    {
      "id": "1ev3bbfrximm8",
      "title": "黃帝素問",
      "relation": "has_part"
    },
    {
      "id": "1ev3bbfsfme4g",
      "title": "靈樞經",
      "relation": "has_part"
    }
  ],
  "indexed_by": [
    {
      "source": "漢書藝文志",
      "source_bid": "1euhm19a23jsw",
      "title_info": "黃帝內經十八卷",
      "summary": "《黃帝内經》十八卷。"
    }
  ],
  "resources": [
    {
      "id": "shidianguji-sibucongkanjingshang",
      "name": "识典古籍",
      "url": "https://www.shidianguji.com/book/SBCK072",
      "metadata": {
        "edition": "四部叢刊景上海涵芬館藏明翻北宋本",
        "version": "v63",
        "total_page": 812,
        "paragraph_count": 737,
        "check_type": "精校"
      },
      "types": [
        "text",
        "image"
      ]
    },
    {
      "name": "维基文库",
      "id": "wikisource",
      "url": "https://zh.wikisource.org/wiki/%E9%BB%83%E5%B8%9D%E5%85%A7%E7%B6%93",
      "types": [
        "text"
      ]
    }
  ],
  "has_text": true,
  "has_image": true,
  "ai_note": "《漢書·藝文志》方技略醫經類著錄《黃帝內經》十八卷，位居醫經七家之首。皇甫謐以《針經》九卷、《素問》九卷共十八卷當之。《素問》之名起於漢晉之間，《隋書·經籍志》始正式著錄。書之成書年代，有西漢說、東漢說，然馬王堆西漢早期墓出土醫書已含其中不少內容，當包含先秦舊說。司馬光《傳家集》早已指出此書為周漢間醫者依託黃帝之名，並非真黃帝所著。來源：溫浚源《漢書藝文志講要》。",
  "measures": [
    {
      "unit": "卷",
      "number": 18
    }
  ],
  "measure_info": "十八卷"
}