{
  "type": "work",
  "title": "食饌次第法",
  "indexed_by": [
    {
      "source": "隋書經籍志",
      "source_bid": "1ev85yncs9ibk",
      "title_info": "《食饌次第法》一卷",
      "summary": "《食饌次第法》一卷梁有《黃帝雜飲食忌》二卷。"
    },
    {
      "source": "國史經籍志",
      "source_bid": "1ev3bb4qxubr4",
      "title_info": "《食饌次第法》一卷",
      "summary": "《食饌次第法》一卷"
    }
  ],
  "juan_count": {
    "number": 1
  },
  "id": "1evcmngeu4su8",
  "emendated_by": [
    {
      "source": "隋書經籍志考證",
      "source_bid": "1evdlszdhf5z4",
      "title_info": "《食饌次第法》一卷",
      "summary": "並不著撰人。\n梁有《劉休食方》一卷,齊冠軍將軍劉休撰,亡。\n《南齊書》本傳:休字弘明,沛郡相人也。初為 馬都尉,奉朝\n請,宋明帝湘東國常侍。明帝頗有好尚,尤嗜飲食,休多藝\n能,爱及鼎味,問無不解。後宫孕者,帝使其男女,無不如\n占。齊建元初,為御史中丞。四年,出為豫章内史,加冠軍將\n軍。卒,年五十四。”\n食饌次第法一卷\n不著撰人。\n梁有《黄帝雜飲食忌》二卷。\n不著撰人。\n案《漢志》經方家之末有《神農黄帝食禁》七卷,嚴氏以為本\n草,未有硫證。案《食禁》即《食忌》。此二卷或即《漢志》七\n卷之遺。《通志略》無“忌”字,豈所見《隋志》果如是乎?"
    }
  ],
  "measures": [
    {
      "unit": "卷",
      "number": 1
    }
  ],
  "measure_info": "一卷"
}
