{
  "type": "work",
  "title": "陳新制",
  "indexed_by": [
    {
      "source": "隋書經籍志",
      "source_bid": "1ev85yncs9ibk",
      "title_info": "《陳新制》六十卷",
      "summary": "《陳新制》六十卷"
    }
  ],
  "juan_count": {
    "number": 60
  },
  "id": "1evcml15stbsw",
  "emendated_by": [
    {
      "source": "隋書經籍志考證",
      "source_bid": "1evdlszdhf5z4",
      "title_info": "陳新制六十卷",
      "summary": "陳新制六十卷\n不著撰人。\n案《唐六典・刑部》注曰:“編録當時制勅,永為法則,以為\n故事。”此陳氏一代之制勅,猶故事之類也。\n以上自應 《漢朝議 》至此,皆刑法之支流。篇敘所謂\n“故事 議,又多零失。今録其見存可觀者,編為刑法篇”\n是也。"
    }
  ],
  "measures": [
    {
      "unit": "卷",
      "number": 60
    }
  ],
  "measure_info": "六十卷"
}
