{
  "type": "work",
  "title": "司馬道子集",
  "indexed_by": [
    {
      "source": "隋書經籍志",
      "source_bid": "1ev85yncs9ibk",
      "title_info": "《司馬道子集》八卷",
      "summary": "晉會稽王《司馬道子集》八卷梁九卷。又有鎮東從事中郎《傅毅集》五卷，亡。"
    }
  ],
  "juan_count": {
    "number": 8
  },
  "id": "1evcmob7etjb4",
  "emendated_by": [
    {
      "source": "隋書經籍志考證",
      "source_bid": "1evdlszdhf5z4",
      "title_info": "《司馬道子集》八卷",
      "summary": "晉會稽王司馬道子集八卷。梁九卷。\n《晉書·簡文三子傳》:會稽文孝王道子,字道子。少以清\n為謝安所稱。年十歲,封琅邪王。後封會稽王。安帝即位,\n累進太傅、揚州牧,領司徒。元興元年,桓玄奏道子酣縱不\n孝,當棄市。詔徙安成郡,使御史杜竹林防衛,竟承玄旨 殺\n之。時年三十九。玄敗,追贈丞相。\n《唐書·經籍志》:晉《會稽王集》八卷。岑刻本不著卷數。\n《唐書·藝文志》:晉《會稽王道子集》八卷。\n嚴氏《全晉文編》:會稽王道子溢日文孝王。《世說言語篇》\n注作“孝文王”。有集八卷。今存疏、啟、書七篇。\n梁又有《鎮東從事中郎傅毅集》五卷,亡。\n傅毅始末末詳。\n《唐書·經籍志》:《傅毅集》五卷。"
    }
  ],
  "measures": [
    {
      "unit": "卷",
      "number": 8
    }
  ],
  "measure_info": "八卷"
}
