{
  "type": "work",
  "title": "五經要義",
  "indexed_by": [
    {
      "source": "隋書經籍志",
      "source_bid": "1ev85yncs9ibk",
      "title_info": "《五經要義》五卷",
      "summary": "《五經要義》五卷梁十七卷，雷氏撰。"
    },
    {
      "source": "新唐書藝文志",
      "source_bid": "1evcs059gkvls",
      "title_info": "五經要義",
      "summary": "五經要義五卷"
    }
  ],
  "id": "1evcpk04yxslc",
  "emendated_by": [
    {
      "source": "隋書經籍志考證",
      "source_bid": "1evdlszdhf5z4",
      "title_info": "五經要義五卷",
      "summary": "五經要義五卷\n不著撰人。\n《唐書·經籍志》:《五經雜義》七卷,劉向撰。《五經通義》九\n卷,劉向撰。《五經要義》五卷,劉向撰。\n《唐書·藝文志》:劉向《五經雜義》七卷,又《五經通義》九卷,\n《五經要義》五卷。\n《玉海藝文》曰:“《文選注》引《五經要義》,《北史·劉芳》引\n《要義》,《世說注》、《隋禮儀志》引《要義》。”\n《經義考》曰:“按《藝文類聚》、《初學記》、杜氏《通典》、《太平\n御覽》並引《要義》文。”\n《孫祠書目》:《五經要義》一卷,洪頤煊集本。\n按本志不知《雜義》、《通義》、《要義》為劉氏書,故皆不著撰\n人,類從於陳、隋人之後。三書之中,《雜義》見於《漢志》,\n自當居首。而本志 去“雜”字,列《通義》後,編次亦失當。\n兩《唐志》則著録甚分明也。又本志此條云《五經要義》五\n卷,梁十七卷,雷氏撰。一似此五卷即雷氏佚存者。《唐\n志》則分析甚明,知五卷者為劉氏書;十七卷者,雷氏書也。"
    }
  ]
}