{
  "type": "work",
  "title": "漢書問答",
  "indexed_by": [
    {
      "source": "宋史藝文志",
      "source_bid": "1evcsw4kt579c",
      "title_info": "《漢書問答》",
      "summary": "《漢書問答》五卷劉珍等"
    },
    {
      "source": "崇文總目",
      "source_bid": "1ev3bb3xyygw0",
      "title_info": "漢書問答五卷",
      "summary": "漢書問答五卷。（闕）。唐沈遵行撰采諸儒爲漢書說者申釋其義有博聞之益然篇第頗差討求未獲闕劉傳以下諸篇"
    },
    {
      "source": "國史經籍志",
      "source_bid": "1ev3bb4qxubr4",
      "title_info": "《漢書問答》五卷",
      "summary": "《漢書問答》五卷（沈遵）",
      "author_info": "沈遵"
    }
  ],
  "id": "1evcsx9bfc8hs",
  "related_works": [
    {
      "id": "1euidlec1g8ow",
      "title": "漢書",
      "relation": "commentary_on"
    }
  ]
}