{
  "type": "work",
  "title": "證俗音字略",
  "indexed_by": [
    {
      "source": "隋書經籍志",
      "source_bid": "1ev85yncs9ibk",
      "title_info": "《證俗音字略》六卷",
      "summary": "《證俗音字略》六卷梁有《詁幼》二卷，顏延之撰；《廣詁幼》一卷，宋給事中荀楷撰。亡。"
    }
  ],
  "id": "1evcpjzv7gkxs",
  "emendated_by": [
    {
      "source": "隋書經籍志考證",
      "source_bid": "1evdlszdhf5z4",
      "title_info": "證俗音字略六卷",
      "summary": "證俗音字略六卷\n《北齊書·文苑傳》:顏之推字介,琅邪臨沂人也。世善《周\n官》、左氏學,之推習禮傳,博覽群書,無不該洽,為湘東王繹\n左常侍。繹自立,以為散騎侍郎,奏舍人事。後為周軍所破,\n將妻子來奔顯祖,除為奉朝請,累遷黄門侍郎。齊亡入周,大\n象末,為御史上士。隋開皇中,太子召為學士,尋以疾終。有\n文三十卷、《家訓》二十篇,並行於世。\n又曰:“之推曾撰《觀我生賦》,文致清遠,其詞有曰:‘予一生\n而三化,備茶苦而藝辛,向使潛於草茅之下,甘為 畝之人,\n毋讀書而學劍,莫抵掌以膏身,委明珠而樂賤,辭白璧以安\n貧,堯、舜不能榮其樸素,桀、 無以汙其清塵,此窮何由而\n至,茲辱安所自臻?而今而後,不敢怨天而泣麟也。自注云:\n*在陽都值侯景殺簡文而篡位,於江陵逢孝元覆滅,至此齊滅\n而三為亡國之人。'”按此賦蓋作於北周時,故云三為亡國之人。其後入隋,\n且四為亡國之人矣。\n又曰:“之推在齊有二子,長日思魯,次曰楚,不忘本也。”《唐\n六典》尚書省主事注:“隋爆帝二年去令史名,每十令史置一主事,雜用才術之士。\n顏憨楚以文學名家,為内史主事。”又《北史·藝術・張 玄傳》云:“内史通事顏\n楚。”按取名 楚者,憨江陵之陷也。或作敏楚,非也。《顏氏家訓》及家廟碑,亦並作\n憨楚。\n《唐日本國見在書目》:《證俗音字略》一卷,顏敏楚撰。\n《唐書·經籍志》:《證俗音略》二卷,顏楚撰。《筆墨法》一\n卷。不著撰人。\n《唐書·藝文志》:“顏之推《筆墨法》一卷,張推《證俗音》三\n卷,顏 楚《證俗音略》一卷。”按《筆墨法》疑是此兩書中篇名。“張推”當\n是“顏之推”之寫誤。\n《宋史·藝文志》:顏之推《證俗音字》四卷,又《字始》三卷。\n《字始》亦疑是篇名。\n《崇文總目》:《正俗音字》四卷,齊黄門侍郎顏之推撰。正時\n俗文字之謬,援諸書為據,凡三十五目。\n任大椿《小學鉤沈》曰:“《北户録》注引《證俗音》凡十二條,又\n《廣韻》引《證俗文》凡四條。”\n按是書諸史記載不一。考顏魯公《家廟碑》,之推撰《證俗\n音字》五卷,則其書實五卷,此六卷;又《訓俗文字略》一卷。\n大抵有《敘録》及 楚所撰節略本在其中,其後或亦删存入\n《家訓》。《家訓》中《書證》、《音辭》兩篇,似即此書之大略。"
    }
  ]
}