{
  "type": "work",
  "title": "周禮馬融注",
  "authors": [
    {
      "name": "馬融",
      "entity_id": "1j9678gg70ht8"
    }
  ],
  "indexed_by": [
    {
      "source": "隋書經籍志",
      "source_bid": "1ev85yncs9ibk",
      "title_info": "《周官禮》十二卷",
      "summary": "《周官禮》十二卷馬融注。"
    }
  ],
  "juan_count": {
    "number": 12
  },
  "description": {
    "text": "马融注。"
  },
  "related_works": [
    {
      "id": "1ev7vo59vzpxc",
      "relation": "commentary_on"
    },
    {
      "id": "1evl7nl7lsg00",
      "title": "周禮",
      "relation": "commentary_on"
    }
  ],
  "id": "1evc5pcsvj280",
  "emendated_by": [
    {
      "source": "隋書經籍志考證",
      "source_bid": "1evdlszdhf5z4",
      "title_info": "周官禮十二卷 馬融注",
      "summary": "馬融有《周易注》,見前易類。\n《漢書·王莽傳》:“元始四年,是歲,徵天下通一藝及有逸\n《禮》、古《書》、《毛詩》、《周官》、《爾雅》,通知其意者,皆詣公\n車。”又《藝文志》:“《周官經》六篇,王莽時,劉歆置博士。”\n苟悅《漢紀》:“劉歆以《周官》十六篇為《周禮》。王莽時,歆奏\n以為經,置博士。”\n馬融《周官傳》序曰:“秦自孝公已下,用商君之法,其政酷烈,\n與《周官》相反。故始皇禁 書,特疾惡,欲絕滅之,搜求焚燒\n之獨悉,是以隱藏百年。孝武帝始除 書之律,開獻書之路,\n既出於山巖屋壁,復入於祕府,五家之儒,莫得見焉。至孝成\n皇帝,達才通人劉向子歆校理祕書,始得列序,著於《録》、\n《略》。然亡其《冬官》一篇,以《考工記》足之。時 儒並出共\n排,以為非是。唯歆獨識,其年尚幼,務在廣覽博觀,又多銳\n精於《春秋》。末年乃知其周公致太平之迹,迹具在斯。奈遭\n天下倉卒,兵革並起,疾疫荒喪,弟子死喪。徒有里人河南\n氏杜子春尚在,永平之初,年且九十,家於南山,能通其讀,頗\n識其說,鄭眾、賈 往受業焉。 、 洪雅博聞,又以經書記\n傳相證明為解, 解行於世,眾解不行。兼攬二家,為備多所\n遺闕。然眾時所解說,近得其實,獨以《書序》言成王既 殷\n命,還歸在豐,作《周官》,則此《周官》也。失之矣。 以為\n六鄉大夫,則家宰以下及六遂,為十五萬家,組千里之地,甚\n謬焉。此比多多,吾甚閔之久矣。至六十為武都守,郡小少\n事,乃述平生之志,著《易》、《尚書》、《詩》、《禮傳》,皆說。惟\n念前業未畢者,唯《周官》。年六十有六,目 意倦,自力補\n之,謂之《周官傳》也。”惠氏《後漢書補注》:《商芸小說》曰:“融在武都七年,\n南郡四年。”\n《後漢書·儒林傳》:《周官經》六篇,前世傳其書,未有名家。\n中興之後,鄭眾傳《周官經》,後馬融作《周官傳》。\n孔穎達《毛詩正義》曰:“漢初為傳訓者,皆與經別行。及馬融\n為《周禮》之注,乃云欲省學者兩讀,故具載本文。然則後漢\n以來,始就經為注。”\n本志篇 曰:“漢時有李氏得《周官》。《周官》蓋周公所制官\n政之法,上於河間獻王,獨闕《冬官》一篇。獻王購以千金,不\n得,遂取《考工記》以補其處,合成六篇,奏之。至王莽時,劉\n歆始置博士,以行於世。河南 氏及杜子春受業於歆,因以\n教授。是後馬融作《周官傳》。”\n《釋文·敘録》:馬融注《周官》十二卷。\n《唐書·經籍志》:《周官》十二卷,馬融傳。\n《唐書·藝文志》:馬融《周官傳》十二卷。\n馬國翰輯本序曰:“融為鄭康成之師,而康成《注》用杜子春及\n鄭大夫父子三家。《疏》引融說,又往往為鄭君所不取。則馬\n《傳》未能精醇,而鄭之不阿所好,均可見已。今輯録一卷。”王\n氏輯存五十五條。"
    }
  ],
  "measures": [
    {
      "unit": "卷",
      "number": 12
    }
  ],
  "measure_info": "十二卷"
}