{
  "type": "work",
  "title": "琴曆頭簿",
  "authors": [],
  "juan_count": {
    "number": 1
  },
  "description": {
    "text": "已亡佚。見《隋書·經籍志》樂類。"
  },
  "indexed_by": [
    {
      "source": "隋書經籍志",
      "source_bid": "1ev85yncs9ibk",
      "title_info": "《琴曆頭簿》一卷",
      "summary": "《琴曆頭簿》一卷"
    },
    {
      "source": "國史經籍志",
      "source_bid": "1ev3bb4qxubr4",
      "title_info": "《琴曆頭簿》一卷",
      "summary": "《琴曆頭簿》一卷"
    }
  ],
  "id": "1evc6as2kxkao",
  "emendated_by": [
    {
      "source": "隋書經籍志考證",
      "source_bid": "1evdlszdhf5z4",
      "title_info": "琴曆頭簿一卷",
      "summary": "不著撰人。《唐書·經籍志》：《琴集曆頭拍簿》一卷。《新志》同。馬國翰玉函山房輯本序曰：「《隋志》有《琴曆頭簿》一卷，《唐志》作《琴集曆頭拍簿》，均不著撰人姓名。《初學記》、《太平御覽》引《琴曆》即此書也。所引互有同異，參校訂輯，凡琴曲三十有八，如《中揮清》、《暢志清》、《蟹行清》、《看客清》、《便僻清》、《婉轉清》六目，他書所未見，足資該聞焉。」"
    }
  ],
  "measures": [
    {
      "unit": "卷",
      "number": 1
    }
  ],
  "measure_info": "一卷"
}
