{
  "type": "work",
  "title": "楊修集",
  "indexed_by": [
    {
      "source": "隋書經籍志",
      "source_bid": "1ev85yncs9ibk",
      "title_info": "《楊修集》一卷",
      "summary": "後漢丞相主簿《楊修集》一卷梁二卷，錄一卷。"
    },
    {
      "source": "舊唐書經籍志",
      "source_bid": "1evcpbhmiqdj4",
      "title_info": "《楊修集》二卷",
      "summary": "《楊修集》二卷"
    }
  ],
  "juan_count": {
    "number": 1
  },
  "id": "1evcmoatdgbuo",
  "emendated_by": [
    {
      "source": "隋書經籍志考證",
      "source_bid": "1evdlszdhf5z4",
      "title_info": "《楊修集》一卷",
      "summary": "《後漢書·楊震傳》:震,弘農華陰人也。中子秉,秉子賜,賜\n子彪,彪子修,字德祖,好學,有俊才,為丞相曹操主簿。操忌\n修,且以袁術之甥,慮為後患,遂因事殺之。修所著賦、頌、\n碑、贊、詩、哀辭、表、記、書凡十五篇。\n又傳注:《續漢書》曰:“人有白修與臨淄侯曹植飲醉共載,從\n司馬門出,謗計 陵侯章。太祖聞之大怒,故遂收殺之,時年\n四十五矣。”\n《魏志·陳思王植傳》注:《典略》曰:“修,建安中,舉孝廉,除\n郎中,丞相請署倉曹屬主簿。是時,軍國多事,修總知外内,\n事皆稱意。自魏太子以下,並爭與交好。臨侯植後以驕縱\n見疏,而植故連綴修不止,修亦不敢自絕。至二十四年秋,公\n以修前後漏泄言教,交關諸侯,乃收殺之。修臨死,謂故人\n曰:“我固自以死之晚也。其意以為坐曹植也。修死後百餘\n日而太祖儿。”\n《文心雕龍才略篇》曰:“路粹、楊修,懷筆記之工。”\n《唐書·經籍》、《藝文志》:《楊修集》二卷。\n汪氏《文選撰人篇目》:後漢楊德祖修有《答臨淄侯 》。\n嚴氏《全後漢文編》:楊修有集二卷。今存《節游賦》、《出征\n賦》、《許昌宫賦》、《神女賦》、《孔雀賦》、《答臨淄侯 》、《司空\n苟爽述費》,凡七篇。\n後漢侍中王 集十一卷"
    }
  ],
  "measures": [
    {
      "unit": "卷",
      "number": 1
    }
  ],
  "measure_info": "一卷"
}
