{
  "type": "work",
  "title": "法書目錄",
  "indexed_by": [
    {
      "source": "隋書經籍志",
      "source_bid": "1ev85yncs9ibk",
      "title_info": "《法書目錄》六卷",
      "summary": "《法書目錄》六卷"
    },
    {
      "source": "舊唐書經籍志",
      "source_bid": "1evcpbhmiqdj4",
      "title_info": "《法書目錄》六卷",
      "summary": "《法書目錄》六卷虞和撰。"
    }
  ],
  "juan_count": {
    "number": 6
  },
  "id": "1evcml28wad4w",
  "emendated_by": [
    {
      "source": "隋書經籍志考證",
      "source_bid": "1evdlszdhf5z4",
      "title_info": "《法書目錄》六卷",
      "summary": "法書目錄六卷\n不著撰人。\n《唐書·經籍志》:《法書目錄》六卷,虞和撰。\n《唐書·藝文志》:虞 《法書目録》六卷。亦複見于經部小學類。\n《南史·文學・丘巨源附傳》:時有虞通之、虞穌,皆有學行,\n皆會稽餘姚人。 位中書郎、廷尉。少好學,居貧屋漏,恐溼\n墳典,乃舒被覆書,書獲全而被大溼。時人以比高鳳。\n唐竇蒙《述書賦》注:宋中書侍郎虞 上明皇帝表,論古今妙\n蹟、正行草楷、紙色標軸、真偽卷數,無不畢備。表本行于世,\n真蹟故起居舍人李造得之。本志集部總集類有《上法書表》一卷,虞和援。\n案張彥遠《法書要録》載虞 《論書表》,題為梁人。今案表\n文實宋明帝泰始六年所上也。 于泰始三年奉詔與前將\n軍巢尚之、司徒參軍徐希秀、淮南太守孫奉伯料簡法書。\n至是年,裝治畢事,乃詣中書省表上。《南史》附傳不載其\n事,此《目錄》六卷,殆隨表上進者。又《述書賦》注云:“梁\n傅昭亦撰《法書目錄》。”《梁書·殷鈞傳》云:“鈞受詔料簡\n西省法書古迹,别為品目。”則為《法書目録》者,不止一家。\n此與兩《唐志》相同,當是虞氏為多。"
    }
  ],
  "measures": [
    {
      "unit": "卷",
      "number": 6
    }
  ],
  "measure_info": "六卷"
}
