{
  "type": "work",
  "title": "元康三年地記",
  "indexed_by": [
    {
      "source": "隋書經籍志",
      "source_bid": "1ev85yncs9ibk",
      "title_info": "《元康三年地記》六卷",
      "summary": "《元康三年地記》六卷"
    },
    {
      "source": "補晋書藝文志",
      "source_bid": "1evfu57n5n37k",
      "summary": "元康三年地記六卷 謹按見《隋志》。《續漢書·郡國志》注引《元康地道記》,《藝文類聚》地部引《元康地記》,皆即此書。"
    }
  ],
  "juan_count": {
    "number": 6
  },
  "id": "1evcml1j6rqio",
  "emendated_by": [
    {
      "source": "隋書經籍志考證",
      "source_bid": "1evdlszdhf5z4",
      "title_info": "《元康三年地記》六卷",
      "summary": "元康三年地記六卷\n不著撰人。\n章氏《考證》:《續漢郡國志》注引《晉元康地道記》。《文選》\n謝靈運《斤竹澗詩》注、《藝文類聚・地部》並稱《元康地記》。\n元康,惠帝年號,與《太康地記》自各為一書。《續漢志注》所\n引稱元康者甚多,固非太康之說。又《隋志》有《元康六年户\n口簿記》。"
    }
  ],
  "measures": [
    {
      "unit": "卷",
      "number": 6
    }
  ],
  "measure_info": "六卷"
}
