{
  "type": "work",
  "title": "皇帝菩薩清淨大舍記",
  "indexed_by": [
    {
      "source": "隋書經籍志",
      "source_bid": "1ev85yncs9ibk",
      "title_info": "《皇帝菩薩清淨大舍記》三卷",
      "summary": "《皇帝菩薩清淨大舍記》三卷謝吳撰，亡。"
    }
  ],
  "id": "1evcmnd3bhp8g",
  "emendated_by": [
    {
      "source": "隋書經籍志考證",
      "source_bid": "1evdlszdhf5z4",
      "title_info": "《皇帝菩薩清淨大舍記》三卷",
      "summary": "皇帝菩薩清淨大捨記三卷 謝吴撰\n謝吴亦作謝是,有《梁書》四十九卷,見史部正史類。\n《太平御覽釋部》:《談戴》曰:“梁高祖崇信佛道,于建業起\n同泰寺,又于故宅立光宅寺,皆窮極工巧, 竭財力。百姓怨\n苦,殆不聊生。自以其身施同泰寺為奴,朝廷其斂珍寶贖之。\n有事佛精苦者, 加以菩薩之號。其下書皆云皇帝菩薩。”\n案史部雜傳類有《梁武皇帝大捨》三卷,嚴撰。與此書\n名、撰人各不同,似乎别為一書。然亦疑嚴即謝,謝\n見《南史·孝義謝貞傳》,貞之族兄也。唐人因武昭王李\n避諱改為謝昊,又轉寫語為謝。《貞傳》云:“魏克江\n陵,貞入長安。 逃難番禺,或因逃難時改姓嚴。貞母出家于宣\n明寺。及陳武帝受禪,還鄉里,供養貞母,將二十年。”\n之事蹟可見者如此。又據本志正史類,仕梁為中書郎,據\n《史通・正史篇》則嘗為祕書監,據《謝宣城集》有與謝洗馬\n吴聯句,則又官太子洗馬, 之仕履可見者又如此。然皆\n無碼證,不知是一是二,疑不能定,姑識于此。《通志·校略)\n云:“《隋志》分類不考,故亦有重複者。”《梁皇大捨記》既出雜傳,又出雜家,則亦\n以為一書矣。然鄭氏但約略言之,非實有據,不足援為定論。"
    }
  ]
}