{
  "id": "1evetxcz5g2dc",
  "type": "work",
  "title": "五經祕表要",
  "authors": [],
  "juan_count": {
    "number": 3
  },
  "emendated_by": [
    {
      "source": "隋書經籍志考證",
      "source_bid": "1evdlszdhf5z4",
      "summary": "梁有《五經祕表要》三卷,亡。\n不著撰人。\n按《五經祕》或是識緯家之說,此表明其要 ?又或是“\n義要”之誤,録祕義之要者,為是書。 緯類有《書、易、詩、孝經、春\n秋、河洛緯祕要》一卷。",
      "title_info": "梁有《五經祕表要》三卷，亡。"
    }
  ],
  "ai_note": "亡佚。隋書經籍志「梁有《五經祕表要》三卷，亡。，亡」。",
  "measures": [
    {
      "unit": "卷",
      "number": 3
    }
  ],
  "measure_info": "三卷"
}
