{
  "id": "1evgp2gprg5xc",
  "type": "work",
  "title": "清同文堂本東西漢演義",
  "authors": [],
  "description": {
    "text": "通俗小說叢書。通行大字本。半葉十一行，行二十六字。繡像甚粗。\n\n此本所收西漢八卷一百回，即甄偉書。東漢八卷三十二回，為清遠道人重編者。",
    "sources": [
      {
        "title": "孫楷第《中國通俗小說書目》卷九·附錄二·叢書目"
      }
    ]
  },
  "juan_count": {
    "number": 0,
    "description": ""
  },
  "indexed_by": [
    {
      "source": "中國通俗小說書目",
      "source_bid": "1evgeo1zzls74",
      "title_info": "清同文堂本東西漢演義",
      "summary": "清同文堂本東西漢演義\n通行大字本。半葉十一行，行二十六字。繡像甚粗。\n\n此本所收西漢八卷一百回，即甄偉書。東漢八卷三十二回，為清遠道人重編者。"
    }
  ]
}
