{
  "type": "work",
  "title": "張率集",
  "juan_count": {
    "number": 38
  },
  "indexed_by": [
    {
      "source": "國史經籍志",
      "source_bid": "1ev3bb4qxubr4",
      "title_info": "《張率集》三十八卷",
      "summary": "《張率集》三十八卷"
    }
  ],
  "description": {
    "text": "《國史經籍志》收錄。",
    "sources": [
      "國史經籍志"
    ]
  },
  "ai_note": "missing_reason: 短title \"張率集\" 唯一候选无作者",
  "id": "1evgqbm89e6f4",
  "measures": [
    {
      "unit": "卷",
      "number": 38
    }
  ],
  "measure_info": "三十八卷"
}
