{
  "type": "work",
  "title": "諸佛要集經",
  "juan_count": {
    "number": 2
  },
  "indexed_by": [
    {
      "source": "國史經籍志",
      "source_bid": "1ev3bb4qxubr4",
      "title_info": "《諸佛要集經》二卷",
      "summary": "《諸佛要集經》二卷"
    }
  ],
  "description": {
    "text": "《國史經籍志》收錄。",
    "sources": [
      "國史經籍志"
    ]
  },
  "id": "1evgpr39kyq68",
  "measures": [
    {
      "unit": "卷",
      "number": 2
    }
  ],
  "measure_info": "二卷",
  "resources": [
    {
      "name": "维基文库",
      "id": "wikisource",
      "url": "https://zh.wikisource.org/wiki/%E8%AB%B8%E4%BD%9B%E8%A6%81%E9%9B%86%E7%B6%93",
      "types": [
        "text"
      ]
    }
  ]
}