{
  "type": "work",
  "title": "詩學禁臠",
  "juan_count": {
    "number": 1
  },
  "indexed_by": [
    {
      "source": "國史經籍志",
      "source_bid": "1ev3bb4qxubr4",
      "title_info": "《詩學禁臠》一卷",
      "summary": "《詩學禁臠》一卷"
    }
  ],
  "description": {
    "text": "《國史經籍志》收錄。",
    "sources": [
      "國史經籍志"
    ]
  },
  "ai_note": "从卷二 ambiguous 新建：unresolved",
  "id": "1evgqgsry7tvk",
  "measures": [
    {
      "unit": "卷",
      "number": 1
    }
  ],
  "measure_info": "一卷",
  "resources": [
    {
      "name": "维基文库",
      "id": "wikisource",
      "url": "https://zh.wikisource.org/wiki/%E8%A9%A9%E5%AD%B8%E7%A6%81%E8%87%A0",
      "types": [
        "text"
      ]
    }
  ]
}