{
  "type": "work",
  "title": "杜正倫集",
  "juan_count": {
    "number": 10
  },
  "indexed_by": [
    {
      "source": "國史經籍志",
      "source_bid": "1ev3bb4qxubr4",
      "title_info": "《杜正倫集》十卷",
      "summary": "《杜正倫集》十卷"
    }
  ],
  "description": {
    "text": "《國史經籍志》收錄。",
    "sources": [
      "國史經籍志"
    ]
  },
  "id": "1evgqbyj7g8ao",
  "measures": [
    {
      "unit": "卷",
      "number": 10
    }
  ],
  "measure_info": "十卷",
  "ai_note": "[CADAL02091118-fix 2026-04-20] OCR 纠错 \"字正倫集\"->\"杜正倫集\""
}