{
  "type": "work",
  "title": "鄧肅析橺集",
  "juan_count": {
    "number": 25
  },
  "indexed_by": [
    {
      "source": "國史經籍志",
      "source_bid": "1ev3bb4qxubr4",
      "title_info": "《鄧肅析橺集》二十五卷",
      "summary": "《鄧肅析橺集》二十五卷"
    }
  ],
  "description": {
    "text": "《國史經籍志》收錄。",
    "sources": [
      "國史經籍志"
    ]
  },
  "id": "1evgqda7lohs0",
  "measures": [
    {
      "unit": "卷",
      "number": 25
    }
  ],
  "measure_info": "二十五卷",
  "ai_note": "[CADAL02091118-fix 2026-04-20] OCR 纠错 \"鄧肅析𣘗集\"→\"鄧肅析橺集\" (位置 3: \"𣘗\"→\"橺\")"
}