{
  "type": "work",
  "title": "農桑輯要",
  "juan_count": {
    "number": 7
  },
  "indexed_by": [
    {
      "source": "國史經籍志",
      "source_bid": "1ev3bb4qxubr4",
      "title_info": "《農桑輯要》七卷",
      "summary": "《農桑輯要》七卷"
    },
    {
      "source": "書目答問",
      "source_bid": "31hyr4yqu8xk9",
      "title_info": "農桑輯要",
      "summary": "《農桑輯要》七卷。{{元至元十年官撰。聚珍本，杭本，福本。}}",
      "author_info": "至元十年官撰"
    }
  ],
  "description": {
    "text": "《國史經籍志》收錄。",
    "sources": [
      "國史經籍志"
    ]
  },
  "ai_note": "从卷二 ambiguous 新建：unresolved",
  "id": "1evgq0jdibh1c",
  "measures": [
    {
      "unit": "卷",
      "number": 7
    }
  ],
  "measure_info": "七卷",
  "resources": [
    {
      "name": "维基文库",
      "id": "wikisource",
      "url": "https://zh.wikisource.org/wiki/%E8%BE%B2%E6%A1%91%E8%BC%AF%E8%A6%81",
      "types": [
        "text"
      ]
    }
  ]
}