{
  "id": "1evha4os0uakh",
  "type": "work",
  "subtype": "poem",
  "title": "丹青引贈曹霸將軍",
  "authors": [
    {
      "name": "杜甫",
      "dynasty": "唐",
      "entity_id": "1j968iupss3ll"
    }
  ],
  "related_works": [
    {
      "id": "1evha3f4fpqf4",
      "title": "唐詩三百首",
      "relation": "collected_in"
    }
  ],
  "resources": [
    {
      "name": "维基文库",
      "id": "wikisource",
      "url": "https://zh.wikisource.org/wiki/%E4%B8%B9%E9%9D%92%E5%BC%95%E8%B4%88%E6%9B%B9%E9%9C%B8%E5%B0%87%E8%BB%8D",
      "types": [
        "text"
      ]
    }
  ]
}