{
  "type": "work",
  "title": "第二次教育統計圖表",
  "authors": [],
  "indexed_by": [
    {
      "source": "國立故宮博物院善本舊籍",
      "source_bid": "",
      "title_info": "《第二次教育統計圖表》不分卷",
      "author_info": "",
      "summary": "《第二次教育統計圖表》不分卷。清光緒三十四年鉛印本。",
      "edition": "清光緒三十四年鉛印本",
      "volume": "故內001258",
      "section": "史部/政書類/教育之屬"
    }
  ],
  "description": {
    "text": "本書收入《國立故宮博物院善本舊籍》（統一編號 故內001258）。清光緒三十四年鉛印本。",
    "sources": [
      "國立故宮博物院善本舊籍"
    ]
  },
  "ai_note": "本 Work 條目從《國立故宮博物院善本舊籍》目錄錄入（catalog: 故內001258）。無作者信息。阶段 5 兜底建立。",
  "juan_count": {
    "number": 0
  },
  "measures": [
    {
      "unit": "卷",
      "number": 0
    }
  ],
  "measure_info": "不分卷",
  "id": "1evkq2v5acqv4",
  "books": [
    "11qki3ktmj37k"
  ]
}