{
  "type": "work",
  "title": "金瘡治事",
  "authors": [],
  "indexed_by": [
    {
      "source": "國立故宮博物院善本舊籍",
      "source_bid": "",
      "title_info": "《金瘡治事》不分卷",
      "author_info": "",
      "summary": "《金瘡治事》不分卷。日本天正七年重應手鈔本。",
      "edition": "日本天正七年重應手鈔本",
      "volume": "故觀013943",
      "section": "子部/醫家類/外科之屬"
    }
  ],
  "description": {
    "text": "本書收入《國立故宮博物院善本舊籍》（統一編號 故觀013943）。日本天正七年重應手鈔本。",
    "sources": [
      "國立故宮博物院善本舊籍"
    ]
  },
  "ai_note": "本 Work 條目從《國立故宮博物院善本舊籍》目錄錄入（catalog: 故觀013943）。無作者信息。阶段 5 兜底建立。",
  "juan_count": {
    "number": 0
  },
  "measures": [
    {
      "unit": "卷",
      "number": 0
    }
  ],
  "measure_info": "不分卷",
  "id": "1evkpyvs2ekg0",
  "books": [
    "11qki0mg9ow00"
  ]
}