{
  "type": "work",
  "title": "重刊增廣分門類林雜說",
  "authors": [],
  "indexed_by": [
    {
      "source": "國立故宮博物院善本舊籍",
      "source_bid": "",
      "title_info": "《重刊增廣分門類林雜說》十五卷",
      "author_info": "",
      "summary": "《重刊增廣分門類林雜說》十五卷。民國間劉承幹刊嘉業堂叢書本。",
      "edition": "民國間劉承幹刊嘉業堂叢書本",
      "volume": "贈善039557-039558",
      "section": "子部/類書類"
    }
  ],
  "description": {
    "text": "本書收入《國立故宮博物院善本舊籍》（統一編號 贈善039557-039558）。民國間劉承幹刊嘉業堂叢書本。",
    "sources": [
      "國立故宮博物院善本舊籍"
    ]
  },
  "ai_note": "本 Work 條目從《國立故宮博物院善本舊籍》目錄錄入（catalog: 贈善039557-039558）。無作者信息。阶段 5 兜底建立。",
  "juan_count": {
    "number": 15
  },
  "measures": [
    {
      "unit": "卷",
      "number": 15
    }
  ],
  "measure_info": "十五卷",
  "id": "1evkpvvlm9vcw",
  "books": [
    "11qkhua2pkw74"
  ]
}