{
  "title": "卷五十八　雜記類",
  "sections": [
    {
      "title": "慈谿縣學記",
      "level": 3,
      "type": "文",
      "work_id": "1evhnsy6tw0sg",
      "author": "王安石"
    },
    {
      "title": "度支副使廳壁題名記",
      "level": 3,
      "type": "文",
      "work_id": "1evhnsybpbe2o",
      "author": "王安石"
    },
    {
      "title": "游褒禪山記",
      "level": 3,
      "type": "文",
      "work_id": "1evhmh2kfbrwg",
      "author": "王安石"
    },
    {
      "title": "芝閣記",
      "level": 3,
      "type": "文",
      "work_id": "1evhnsylkuosg",
      "author": "王安石"
    },
    {
      "title": "傷仲永",
      "level": 3,
      "type": "文",
      "work_id": "1evhnsyqngikg",
      "author": "王安石"
    },
    {
      "title": "新城游北山記",
      "level": 3,
      "type": "文",
      "work_id": "1evhnsyvs905c",
      "author": "晁補之"
    }
  ]
}