{
  "type": "book",
  "title": "通鑒紀事本末",
  "work_id": "1ev3bac6hpl34",
  "edition": "欽定四庫全書薈要·摛藻堂本",
  "contained_in": [
    {
      "id": "1ahjf6q3b8hds",
      "volume_index": [
        206,
        207,
        208,
        209
      ]
    }
  ],
  "resources": [
    {
      "name": "摛藻堂四庫全書薈要·第206冊",
      "url": "https://commons.wikimedia.org/wiki/File:摛藻堂四庫全書薈要.第206冊.史部120冊.djvu",
      "types": [
        "image"
      ]
    },
    {
      "name": "摛藻堂四庫全書薈要·第207冊",
      "url": "https://commons.wikimedia.org/wiki/File:摛藻堂四庫全書薈要.第207冊.史部121冊.djvu",
      "types": [
        "image"
      ]
    },
    {
      "name": "摛藻堂四庫全書薈要·第208冊",
      "url": "https://commons.wikimedia.org/wiki/File:摛藻堂四庫全書薈要.第208冊.史部122冊.djvu",
      "types": [
        "image"
      ]
    },
    {
      "name": "摛藻堂四庫全書薈要·第209冊",
      "url": "https://commons.wikimedia.org/wiki/File:摛藻堂四庫全書薈要.第209冊.史部123冊.djvu",
      "types": [
        "image"
      ]
    }
  ],
  "id": "11q7m1s98tse8"
}