{
  "id": "11qkhyy2qqby8",
  "type": "book",
  "title": "古刻叢鈔",
  "contained_in": [
    {
      "id": "1ahwlq4d3tjwg"
    }
  ],
  "section": "史部",
  "edition": "清乾隆道光間刊知不足齋叢書之一",
  "resources": [
    {
      "id": "npm-rarebooks",
      "name": "國立故宮博物院善本古籍",
      "short_name": "故宮善本",
      "url": "https://rarebooks-maps.npm.edu.tw/index.php?act=Archive/search/1-20/eyJwYWdlaW5nIjogIjEtMjAiLCAic2VhcmNoIjogW3siZmllbGQiOiAiQ21uTnVtYmVyIiwgInZhbHVlIjogIlx1NjU0NVx1ODljMDAwMTgyOCJ9XSwgInBxZmlsdGVyIjogW10sICJ0cGZpbHRlciI6IHt9fQ%3D%3D",
      "types": [
        "physical"
      ],
      "metadata": {
        "item_id": "故觀001828",
        "acckey": "d02520897bc06299203ced164316aa2d"
      }
    }
  ],
  "metadata": {
    "npm_item_id": "故觀001828",
    "npm_acckey": "d02520897bc06299203ced164316aa2d"
  },
  "work_id": "1ev3bb4byrhmo"
}