{
  "id": "11qki3optbxts",
  "type": "book",
  "title": "聖祖庭訓格言",
  "contained_in": [
    {
      "id": "1ahwlq4d3tjwg"
    }
  ],
  "section": "子部",
  "edition": "清雍正八年武英殿刊滿文本",
  "resources": [
    {
      "id": "npm-rarebooks",
      "name": "國立故宮博物院善本古籍",
      "short_name": "故宮善本",
      "url": "https://rarebooks-maps.npm.edu.tw/index.php?act=Archive/search/1-20/eyJwYWdlaW5nIjogIjEtMjAiLCAic2VhcmNoIjogW3siZmllbGQiOiAiQ21uTnVtYmVyIiwgInZhbHVlIjogIlx1NjU0NVx1NmVmZjAwMDQxMC0wMDA0MTEifV0sICJwcWZpbHRlciI6IFtdLCAidHBmaWx0ZXIiOiB7fX0%3D",
      "types": [
        "physical"
      ],
      "metadata": {
        "item_id": "故滿000410-000411",
        "acckey": "040cc6203e6b052bf061622e31495bfb"
      }
    }
  ],
  "metadata": {
    "npm_item_id": "故滿000410-000411",
    "npm_acckey": "040cc6203e6b052bf061622e31495bfb"
  },
  "work_id": "1evkpo960dhc0"
}