{
  "id": "11qki0g10pslc",
  "type": "book",
  "title": "儀禮漢讀考",
  "contained_in": [
    {
      "id": "1ahwlq4d3tjwg"
    }
  ],
  "section": "經部",
  "edition": "清乾隆道光間金壇段氏刊經韻樓叢書之一",
  "resources": [
    {
      "id": "npm-rarebooks",
      "name": "國立故宮博物院善本古籍",
      "short_name": "故宮善本",
      "url": "https://rarebooks-maps.npm.edu.tw/index.php?act=Archive/search/1-20/eyJwYWdlaW5nIjogIjEtMjAiLCAic2VhcmNoIjogW3siZmllbGQiOiAiQ21uTnVtYmVyIiwgInZhbHVlIjogIlx1NjU0NVx1ODljMDAxMjQxOSJ9XSwgInBxZmlsdGVyIjogW10sICJ0cGZpbHRlciI6IHt9fQ%3D%3D",
      "types": [
        "physical"
      ],
      "metadata": {
        "item_id": "故觀012419",
        "acckey": "971ddd5b33f270580faf1ade68ae540f"
      }
    }
  ],
  "metadata": {
    "npm_item_id": "故觀012419",
    "npm_acckey": "971ddd5b33f270580faf1ade68ae540f"
  },
  "work_id": "31hyr4yqrfsno"
}