{
  "id": "11qkht0o8iqyo",
  "type": "book",
  "title": "樂安縣志",
  "contained_in": [
    {
      "id": "1ahwlq4d3tjwg"
    }
  ],
  "section": "史部",
  "edition": "清雍正十一年刊本",
  "resources": [
    {
      "id": "npm-rarebooks",
      "name": "國立故宮博物院善本古籍",
      "short_name": "故宮善本",
      "url": "https://rarebooks-maps.npm.edu.tw/index.php?act=Archive/search/1-20/eyJwYWdlaW5nIjogIjEtMjAiLCAic2VhcmNoIjogW3siZmllbGQiOiAiQ21uTnVtYmVyIiwgInZhbHVlIjogIlx1OGQwOFx1NTU4NDAxNzQxNC0wMTc0MTgifV0sICJwcWZpbHRlciI6IFtdLCAidHBmaWx0ZXIiOiB7fX0%3D",
      "types": [
        "physical"
      ],
      "metadata": {
        "item_id": "贈善017414-017418",
        "acckey": "498d7af12486d4c9e8f086c7eda767ad"
      }
    }
  ],
  "metadata": {
    "npm_item_id": "贈善017414-017418",
    "npm_acckey": "498d7af12486d4c9e8f086c7eda767ad"
  },
  "work_id": "1evkpt1tl5hj4"
}