{
  "id": "11qki66oox8g0",
  "type": "book",
  "title": "海叟集",
  "contained_in": [
    {
      "id": "1ahwlq4d3tjwg"
    }
  ],
  "section": "集部",
  "edition": "清桐鄉汪氏裘抒樓傳鈔明萬曆三十七年松江張所望刊本",
  "resources": [
    {
      "id": "npm-rarebooks",
      "name": "國立故宮博物院善本古籍",
      "short_name": "故宮善本",
      "url": "https://rarebooks-maps.npm.edu.tw/index.php?act=Archive/search/1-20/eyJwYWdlaW5nIjogIjEtMjAiLCAic2VhcmNoIjogW3siZmllbGQiOiAiQ21uTnVtYmVyIiwgInZhbHVlIjogIlx1NWU3M1x1NTcxNjAxMzU3MSJ9XSwgInBxZmlsdGVyIjogW10sICJ0cGZpbHRlciI6IHt9fQ%3D%3D",
      "types": [
        "physical"
      ],
      "metadata": {
        "item_id": "平圖013571",
        "acckey": "2aebb74a9900c29ef6b73a54d5bb34fe"
      }
    }
  ],
  "metadata": {
    "npm_item_id": "平圖013571",
    "npm_acckey": "2aebb74a9900c29ef6b73a54d5bb34fe"
  },
  "work_id": "1ev3bd9cnfi0w"
}