{
  "id": "11qki41xxny0w",
  "type": "book",
  "title": "讀四書叢說",
  "contained_in": [
    {
      "id": "1ahwlq4d3tjwg"
    }
  ],
  "section": "經部",
  "edition": "元至正六年刊修補本",
  "resources": [
    {
      "id": "npm-rarebooks",
      "name": "國立故宮博物院善本古籍",
      "short_name": "故宮善本",
      "url": "https://rarebooks-maps.npm.edu.tw/index.php?act=Archive/search/1-20/eyJwYWdlaW5nIjogIjEtMjAiLCAic2VhcmNoIjogW3siZmllbGQiOiAiQ21uTnVtYmVyIiwgInZhbHVlIjogIlx1NWU3M1x1NTcxNjAwMDU2OC0wMDA1NzAifV0sICJwcWZpbHRlciI6IFtdLCAidHBmaWx0ZXIiOiB7fX0%3D",
      "types": [
        "physical"
      ],
      "metadata": {
        "item_id": "平圖000568-000570",
        "acckey": "39a9af7f312f47a57e92854559a1258b"
      }
    }
  ],
  "metadata": {
    "npm_item_id": "平圖000568-000570",
    "npm_acckey": "39a9af7f312f47a57e92854559a1258b"
  },
  "work_id": "1evga1wv20w74"
}