{
  "id": "11qkh5wj7mq68",
  "type": "book",
  "title": "明賢蒙正錄",
  "contained_in": [
    {
      "id": "1ahwlq4d3tjwg"
    }
  ],
  "section": "史部",
  "edition": "清光緒八年津河廣仁堂校刊本",
  "resources": [
    {
      "id": "npm-rarebooks",
      "name": "國立故宮博物院善本古籍",
      "short_name": "故宮善本",
      "url": "https://rarebooks-maps.npm.edu.tw/index.php?act=Archive/search/1-20/eyJwYWdlaW5nIjogIjEtMjAiLCAic2VhcmNoIjogW3siZmllbGQiOiAiQ21uTnVtYmVyIiwgInZhbHVlIjogIlx1OGQwOFx1NTU4NDAwMDc4MC0wMDA3ODEifV0sICJwcWZpbHRlciI6IFtdLCAidHBmaWx0ZXIiOiB7fX0%3D",
      "types": [
        "physical"
      ],
      "metadata": {
        "item_id": "贈善000780-000781",
        "acckey": "51016a4864e33631968c380c035dba32"
      }
    }
  ],
  "metadata": {
    "npm_item_id": "贈善000780-000781",
    "npm_acckey": "51016a4864e33631968c380c035dba32"
  },
  "work_id": "1evka73xb5mo0"
}