{
  "id": "11qkhvhcxxczk",
  "type": "book",
  "title": "三易備遺",
  "contained_in": [
    {
      "id": "1ahwlq4d3tjwg"
    }
  ],
  "section": "經部",
  "edition": "清乾隆間寫文淵閣四庫全書本",
  "resources": [
    {
      "id": "npm-rarebooks",
      "name": "國立故宮博物院善本古籍",
      "short_name": "故宮善本",
      "url": "https://rarebooks-maps.npm.edu.tw/index.php?act=Archive/search/1-20/eyJwYWdlaW5nIjogIjEtMjAiLCAic2VhcmNoIjogW3siZmllbGQiOiAiQ21uTnVtYmVyIiwgInZhbHVlIjogIlx1NjU0NVx1NWVhYjAwMDM0Ni0wMDAzNDkifV0sICJwcWZpbHRlciI6IFtdLCAidHBmaWx0ZXIiOiB7fX0%3D",
      "types": [
        "physical"
      ],
      "metadata": {
        "item_id": "故庫000346-000349",
        "acckey": "d808a782a87f5f8d6c3f60d6d79807b6"
      }
    }
  ],
  "metadata": {
    "npm_item_id": "故庫000346-000349",
    "npm_acckey": "d808a782a87f5f8d6c3f60d6d79807b6"
  },
  "work_id": "1ev0r91de6ebk"
}