{
  "id": "11qki7h7vtslc",
  "type": "book",
  "title": "乾隆南巡紀程圖",
  "contained_in": [
    {
      "id": "1ahwlq4d3tjwg"
    }
  ],
  "section": "史部",
  "edition": "",
  "resources": [
    {
      "id": "npm-rarebooks",
      "name": "國立故宮博物院善本古籍",
      "short_name": "故宮善本",
      "url": "https://rarebooks-maps.npm.edu.tw/index.php?act=Archive/search/1-20/eyJwYWdlaW5nIjogIjEtMjAiLCAic2VhcmNoIjogW3siZmllbGQiOiAiQ21uTnVtYmVyIiwgInZhbHVlIjogIlx1NWU3M1x1NTcxNjAyMDgwMy0wMjA4MTgifV0sICJwcWZpbHRlciI6IFtdLCAidHBmaWx0ZXIiOiB7fX0%3D",
      "types": [
        "image",
        "physical"
      ],
      "metadata": {
        "item_id": "平圖020803-020818",
        "acckey": "6ed6c08a94e16e05d7e684f36327c107",
        "digital_pages": 102
      }
    }
  ],
  "metadata": {
    "npm_item_id": "平圖020803-020818",
    "npm_acckey": "6ed6c08a94e16e05d7e684f36327c107"
  },
  "work_id": "1evkq4j69mww0"
}