{
  "id": "11qkhw1f697nk",
  "type": "book",
  "title": "春秋左氏傳事類始末",
  "contained_in": [
    {
      "id": "1ahwlq4d3tjwg"
    }
  ],
  "section": "經部",
  "edition": "清乾隆間寫文淵閣四庫全書本",
  "resources": [
    {
      "id": "npm-rarebooks",
      "name": "國立故宮博物院善本古籍",
      "short_name": "故宮善本",
      "url": "https://rarebooks-maps.npm.edu.tw/index.php?act=Archive/search/1-20/eyJwYWdlaW5nIjogIjEtMjAiLCAic2VhcmNoIjogW3siZmllbGQiOiAiQ21uTnVtYmVyIiwgInZhbHVlIjogIlx1NjU0NVx1NWVhYjAwNzc4OS0wMDc3OTQifV0sICJwcWZpbHRlciI6IFtdLCAidHBmaWx0ZXIiOiB7fX0%3D",
      "types": [
        "physical"
      ],
      "metadata": {
        "item_id": "故庫007789-007794",
        "acckey": "45f46f58e93d0b3def07cf777c697576"
      }
    }
  ],
  "metadata": {
    "npm_item_id": "故庫007789-007794",
    "npm_acckey": "45f46f58e93d0b3def07cf777c697576"
  },
  "work_id": "1ev3bac6utjwg"
}