{
  "id": "11qkhypnmoef4",
  "type": "book",
  "title": "孟子",
  "contained_in": [
    {
      "id": "1ahwlq4d3tjwg"
    }
  ],
  "section": "經部",
  "edition": "日本江戶間影抄慶長間活字本",
  "resources": [
    {
      "id": "npm-rarebooks",
      "name": "國立故宮博物院善本古籍",
      "short_name": "故宮善本",
      "url": "https://rarebooks-maps.npm.edu.tw/index.php?act=Archive/search/1-20/eyJwYWdlaW5nIjogIjEtMjAiLCAic2VhcmNoIjogW3siZmllbGQiOiAiQ21uTnVtYmVyIiwgInZhbHVlIjogIlx1NjU0NVx1ODljMDAwMTE1OS0wMDExNjMifV0sICJwcWZpbHRlciI6IFtdLCAidHBmaWx0ZXIiOiB7fX0%3D",
      "types": [
        "physical"
      ],
      "metadata": {
        "item_id": "故觀001159-001163",
        "acckey": "96a92072cc58c3c112fa6452958d358f"
      }
    }
  ],
  "metadata": {
    "npm_item_id": "故觀001159-001163",
    "npm_acckey": "96a92072cc58c3c112fa6452958d358f"
  },
  "work_id": "1evgor1ow6l8g"
}