{
  "id": "11qkhzukd8z5s",
  "type": "book",
  "title": "岑嘉州詩集",
  "contained_in": [
    {
      "id": "1ahwlq4d3tjwg"
    }
  ],
  "section": "集部",
  "edition": "日本京都寬保元年水玉堂刊本",
  "resources": [
    {
      "id": "npm-rarebooks",
      "name": "國立故宮博物院善本古籍",
      "short_name": "故宮善本",
      "url": "https://rarebooks-maps.npm.edu.tw/index.php?act=Archive/search/1-20/eyJwYWdlaW5nIjogIjEtMjAiLCAic2VhcmNoIjogW3siZmllbGQiOiAiQ21uTnVtYmVyIiwgInZhbHVlIjogIlx1NjU0NVx1ODljMDAwNzU5My0wMDc1OTQifV0sICJwcWZpbHRlciI6IFtdLCAidHBmaWx0ZXIiOiB7fX0%3D",
      "types": [
        "image",
        "physical"
      ],
      "metadata": {
        "item_id": "故觀007593-007594",
        "acckey": "fb21ce8b39a631c3bf738d7c7fe8a823",
        "digital_pages": 125
      }
    }
  ],
  "metadata": {
    "npm_item_id": "故觀007593-007594",
    "npm_acckey": "fb21ce8b39a631c3bf738d7c7fe8a823"
  },
  "work_id": "1evkan3rcv7r4"
}