{
  "id": "11qki04910i68",
  "type": "book",
  "title": "唐詩百名家全集",
  "contained_in": [
    {
      "id": "1ahwlq4d3tjwg"
    }
  ],
  "section": "集部",
  "edition": "清康熙壬午(四十一年)洞庭席氏琴川書屋刊光緒八年印本",
  "resources": [
    {
      "id": "npm-rarebooks",
      "name": "國立故宮博物院善本古籍",
      "short_name": "故宮善本",
      "url": "https://rarebooks-maps.npm.edu.tw/index.php?act=Archive/search/1-20/eyJwYWdlaW5nIjogIjEtMjAiLCAic2VhcmNoIjogW3siZmllbGQiOiAiQ21uTnVtYmVyIiwgInZhbHVlIjogIlx1NjU0NVx1ODljMDAwOTY4NS0wMDk3NDgifV0sICJwcWZpbHRlciI6IFtdLCAidHBmaWx0ZXIiOiB7fX0%3D",
      "types": [
        "physical"
      ],
      "metadata": {
        "item_id": "故觀009685-009748",
        "acckey": "01e4c8b229e575c38bacfd3cfb99f6ef"
      }
    }
  ],
  "metadata": {
    "npm_item_id": "故觀009685-009748",
    "npm_acckey": "01e4c8b229e575c38bacfd3cfb99f6ef"
  },
  "work_id": "1evkanpjpqeio"
}