{
  "id": "11qkhtcwzlreo",
  "type": "book",
  "title": "繹史",
  "contained_in": [
    {
      "id": "1ahwlq4d3tjwg"
    }
  ],
  "section": "史部",
  "edition": "清光緒二十三年石印本",
  "resources": [
    {
      "id": "npm-rarebooks",
      "name": "國立故宮博物院善本古籍",
      "short_name": "故宮善本",
      "url": "https://rarebooks-maps.npm.edu.tw/index.php?act=Archive/search/1-20/eyJwYWdlaW5nIjogIjEtMjAiLCAic2VhcmNoIjogW3siZmllbGQiOiAiQ21uTnVtYmVyIiwgInZhbHVlIjogIlx1OGQwOFx1NTU4NDAyMjc4NC0wMjI4MDYifV0sICJwcWZpbHRlciI6IFtdLCAidHBmaWx0ZXIiOiB7fX0%3D",
      "types": [
        "physical"
      ],
      "metadata": {
        "item_id": "贈善022784-022806",
        "acckey": "f9c9d9821427043c8ca18a82264067cf"
      }
    }
  ],
  "metadata": {
    "npm_item_id": "贈善022784-022806",
    "npm_acckey": "f9c9d9821427043c8ca18a82264067cf"
  },
  "work_id": "1evkpulflu0w0"
}