{
  "id": "11qkhttlvffuo",
  "type": "book",
  "title": "復堂文續",
  "contained_in": [
    {
      "id": "1ahwlq4d3tjwg"
    }
  ],
  "section": "集部",
  "edition": "清光緒二十七年刊刻鵠齋叢書本",
  "resources": [
    {
      "id": "npm-rarebooks",
      "name": "國立故宮博物院善本古籍",
      "short_name": "故宮善本",
      "url": "https://rarebooks-maps.npm.edu.tw/index.php?act=Archive/search/1-20/eyJwYWdlaW5nIjogIjEtMjAiLCAic2VhcmNoIjogW3siZmllbGQiOiAiQ21uTnVtYmVyIiwgInZhbHVlIjogIlx1OGQwOFx1NTU4NDAyNzQ2Mi0wMjc0NjUifV0sICJwcWZpbHRlciI6IFtdLCAidHBmaWx0ZXIiOiB7fX0%3D",
      "types": [
        "physical"
      ],
      "metadata": {
        "item_id": "贈善027462-027465",
        "acckey": "55d1ccaa85105092461292bc998c6d5e"
      }
    }
  ],
  "metadata": {
    "npm_item_id": "贈善027462-027465",
    "npm_acckey": "55d1ccaa85105092461292bc998c6d5e"
  },
  "work_id": "31hyr4yqxzrwm"
}