{
  "id": "11qki2hjq6wow",
  "type": "book",
  "title": "大事記",
  "contained_in": [
    {
      "id": "1ahwlq4d3tjwg"
    }
  ],
  "section": "史部",
  "edition": "清嘉慶間續刊武英殿聚珍本",
  "resources": [
    {
      "id": "npm-rarebooks",
      "name": "國立故宮博物院善本古籍",
      "short_name": "故宮善本",
      "url": "https://rarebooks-maps.npm.edu.tw/index.php?act=Archive/search/1-20/eyJwYWdlaW5nIjogIjEtMjAiLCAic2VhcmNoIjogW3siZmllbGQiOiAiQ21uTnVtYmVyIiwgInZhbHVlIjogIlx1NjU0NVx1NmJiZjAxNTgxMC0wMTU4MjEifV0sICJwcWZpbHRlciI6IFtdLCAidHBmaWx0ZXIiOiB7fX0%3D",
      "types": [
        "physical"
      ],
      "metadata": {
        "item_id": "故殿015810-015821",
        "acckey": "bb3bb2aa4dfa5ad85b3e95d73a545664"
      }
    }
  ],
  "metadata": {
    "npm_item_id": "故殿015810-015821",
    "npm_acckey": "bb3bb2aa4dfa5ad85b3e95d73a545664"
  },
  "work_id": "1evgph51x1gxs"
}