{
  "id": "11qkhsq68g5q8",
  "type": "book",
  "title": "汜水縣志",
  "contained_in": [
    {
      "id": "1ahwlq4d3tjwg"
    }
  ],
  "section": "史部",
  "edition": "民國十七年鉛印本",
  "resources": [
    {
      "id": "npm-rarebooks",
      "name": "國立故宮博物院善本古籍",
      "short_name": "故宮善本",
      "url": "https://rarebooks-maps.npm.edu.tw/index.php?act=Archive/search/1-20/eyJwYWdlaW5nIjogIjEtMjAiLCAic2VhcmNoIjogW3siZmllbGQiOiAiQ21uTnVtYmVyIiwgInZhbHVlIjogIlx1OGQwOFx1NTU4NDAxMzMyOS0wMTMzMzYifV0sICJwcWZpbHRlciI6IFtdLCAidHBmaWx0ZXIiOiB7fX0%3D",
      "types": [
        "physical"
      ],
      "metadata": {
        "item_id": "贈善013329-013336",
        "acckey": "bc4b351f49d65ead8c410c4e346c3e08"
      }
    }
  ],
  "metadata": {
    "npm_item_id": "贈善013329-013336",
    "npm_acckey": "bc4b351f49d65ead8c410c4e346c3e08"
  },
  "work_id": "1evke1t2xrym8"
}